poker_log_parser-0.1.3.dist-info/METADATA
poker_log_parser-0.1.3.dist-info/WHEEL
poker_log_parser-0.1.3.dist-info/license_files/LICENSE.txt
poker_log_parser/__init__.py
poker_log_parser/__init__.pyi
poker_log_parser/py.typed
poker_log_parser/poker_log_parser.cp39-win_amd64.pyd
poker_log_parser-0.1.3.dist-info/RECORD
