Metadata-Version: 2.1
Name: poker-log-parser
Version: 0.1.3
Classifier: Development Status :: 4 - Beta
Classifier: Programming Language :: Rust
Classifier: Programming Language :: Python :: Implementation :: CPython
Classifier: Programming Language :: Python :: Implementation :: PyPy
License-File: LICENSE.txt
Summary: A blazingly-fast Rust/Python library for parsing poker hand histories
Keywords: poker,hand history,hand histories,poker parser,PokerStars,Pluribus,OnGame
Author: Djordje Pepic
Author-email: djordje.pepic.10@gmail.com
Requires-Python: >=3.7
